{
  "status": 0,
  "result": [
    {
      "createdById": "0054W00000A3g2OQAR",
      "createdByName": "Admin User",
      "createdDate": "2020-08-20T22:27:35.000Z",
      "fileName": "reports/unfiled$public/SampleReportDocumentLibrary.report",
      "fullName": "unfiled$public/SampleReportDocumentLibrary",
      "id": "00O4W000002yTm5UAE",
      "lastModifiedById": "0054W00000A3g2OQAR",
      "lastModifiedByName": "Admin User",
      "lastModifiedDate": "2020-08-20T22:27:35.000Z",
      "manageableState": "unmanaged",
      "type": "Report"
    },
    {
      "createdById": "0054W00000A3g2OQAR",
      "createdByName": "Admin User",
      "createdDate": "2020-08-20T22:27:35.000Z",
      "fileName": "reports/unfiled$public/SampleReportLastModifiedBy.report",
      "fullName": "unfiled$public/SampleReportLastModifiedBy",
      "id": "00O4W000002yTlxUAE",
      "lastModifiedById": "0054W00000A3g2OQAR",
      "lastModifiedByName": "Admin User",
      "lastModifiedDate": "2020-08-20T22:27:35.000Z",
      "manageableState": "unmanaged",
      "type": "Report"
    },
    {
      "createdById": "0054W00000A3g2OQAR",
      "createdByName": "Admin User",
      "createdDate": "2020-08-20T22:27:35.000Z",
      "fileName": "reports/unfiled$public/SampleReportLeadsbyLeadSource.report",
      "fullName": "unfiled$public/SampleReportLeadsbyLeadSource",
      "id": "00O4W000003nxfYUAQ",
      "lastModifiedById": "0054W00000A3g2OQAR",
      "lastModifiedByName": "Admin User",
      "lastModifiedDate": "2020-08-20T22:27:35.000Z",
      "manageableState": "unmanaged",
      "type": "Report"
    },
    {
      "createdById": "0054W00000A3g2OQAR",
      "createdByName": "Admin User",
      "createdDate": "2020-08-20T22:27:35.000Z",
      "fileName": "reports/unfiled$public/SampleReportofSolutions.report",
      "fullName": "unfiled$public/SampleReportofSolutions",
      "id": "00O4W000002yTltUAE",
      "lastModifiedById": "0054W00000A3g2OQAR",
      "lastModifiedByName": "Admin User",
      "lastModifiedDate": "2020-08-20T22:27:35.000Z",
      "manageableState": "unmanaged",
      "type": "Report"
    },
    {
      "createdById": "0054W00000A3g2OQAR",
      "createdByName": "Admin User",
      "createdDate": "2020-08-20T22:27:35.000Z",
      "fileName": "reports/unfiled$public/SampleReportSalesPipelinebyStage.report",
      "fullName": "unfiled$public/SampleReportSalesPipelinebyStage",
      "id": "00O4W000003nxfUUAQ",
      "lastModifiedById": "0054W00000A3g2OQAR",
      "lastModifiedByName": "Admin User",
      "lastModifiedDate": "2020-08-20T22:27:35.000Z",
      "manageableState": "unmanaged",
      "type": "Report"
    },
    {
      "createdById": "0054W00000A3g2OQAR",
      "createdByName": "Admin User",
      "createdDate": "2020-08-20T22:27:35.000Z",
      "fileName": "reports/unfiled$public/SampleReportOpenDeals.report",
      "fullName": "unfiled$public/SampleReportOpenDeals",
      "id": "00O4W000003nxfWUAQ",
      "lastModifiedById": "0054W00000A3g2OQAR",
      "lastModifiedByName": "Admin User",
      "lastModifiedDate": "2020-08-20T22:27:35.000Z",
      "manageableState": "unmanaged",
      "type": "Report"
    },
    {
      "createdById": "0054W00000A3g2OQAR",
      "createdByName": "Admin User",
      "createdDate": "2020-08-20T22:27:35.000Z",
      "fileName": "reports/unfiled$public/SampleReportClosedSales.report",
      "fullName": "unfiled$public/SampleReportClosedSales",
      "id": "00O4W000003nxfTUAQ",
      "lastModifiedById": "0054W00000A3g2OQAR",
      "lastModifiedByName": "Admin User",
      "lastModifiedDate": "2020-08-20T22:27:35.000Z",
      "manageableState": "unmanaged",
      "type": "Report"
    },
    {
      "createdById": "0054W00000A3g2OQAR",
      "createdByName": "Admin User",
      "createdDate": "2020-08-20T22:27:35.000Z",
      "fileName": "reports/unfiled$public/SampleReportSalesLeaderboard.report",
      "fullName": "unfiled$public/SampleReportSalesLeaderboard",
      "id": "00O4W000003nxfbUAA",
      "lastModifiedById": "0054W00000A3g2OQAR",
      "lastModifiedByName": "Admin User",
      "lastModifiedDate": "2020-08-20T22:27:35.000Z",
      "manageableState": "unmanaged",
      "type": "Report"
    },
    {
      "createdById": "0054W00000A3g2OQAR",
      "createdByName": "Admin User",
      "createdDate": "2020-08-20T22:27:35.000Z",
      "fileName": "reports/unfiled$public/SampleReportPipelineByCloseMonth.report",
      "fullName": "unfiled$public/SampleReportPipelineByCloseMonth",
      "id": "00O4W000003nxfXUAQ",
      "lastModifiedById": "0054W00000A3g2OQAR",
      "lastModifiedByName": "Admin User",
      "lastModifiedDate": "2020-08-20T22:27:35.000Z",
      "manageableState": "unmanaged",
      "type": "Report"
    },
    {
      "createdById": "0054W00000A3g2OQAR",
      "createdByName": "Admin User",
      "createdDate": "2020-08-20T22:27:35.000Z",
      "fileName": "reports/unfiled$public/SampleReportofOpportunities.report",
      "fullName": "unfiled$public/SampleReportofOpportunities",
      "id": "00O4W000002yTlyUAE",
      "lastModifiedById": "0054W00000A3g2OQAR",
      "lastModifiedByName": "Admin User",
      "lastModifiedDate": "2020-08-20T22:27:35.000Z",
      "manageableState": "unmanaged",
      "type": "Report"
    },
    {
      "createdById": "0054W00000A3g2OQAR",
      "createdByName": "Admin User",
      "createdDate": "2020-08-20T22:27:35.000Z",
      "fileName": "reports/unfiled$public/SampleReportofLeads.report",
      "fullName": "unfiled$public/SampleReportofLeads",
      "id": "00O4W000002yTluUAE",
      "lastModifiedById": "0054W00000A3g2OQAR",
      "lastModifiedByName": "Admin User",
      "lastModifiedDate": "2020-08-20T22:27:35.000Z",
      "manageableState": "unmanaged",
      "type": "Report"
    },
    {
      "createdById": "0054W00000A3g2OQAR",
      "createdByName": "Admin User",
      "createdDate": "2020-08-20T22:27:35.000Z",
      "fileName": "reports/unfiled$public/SampleReportCasesStatusbyRep.report",
      "fullName": "unfiled$public/SampleReportCasesStatusbyRep",
      "id": "00O4W000003nxfcUAA",
      "lastModifiedById": "0054W00000A3g2OQAR",
      "lastModifiedByName": "Admin User",
      "lastModifiedDate": "2020-08-20T22:27:35.000Z",
      "manageableState": "unmanaged",
      "type": "Report"
    },
    {
      "createdById": "0054W00000A3g2OQAR",
      "createdByName": "Admin User",
      "createdDate": "2020-08-20T22:27:35.000Z",
      "fileName": "reports/unfiled$public/SampleReportofDocuments.report",
      "fullName": "unfiled$public/SampleReportofDocuments",
      "id": "00O4W000003nxfgUAA",
      "lastModifiedById": "0054W00000A3g2OQAR",
      "lastModifiedByName": "Admin User",
      "lastModifiedDate": "2020-08-20T22:27:35.000Z",
      "manageableState": "unmanaged",
      "type": "Report"
    },
    {
      "createdById": "0054W00000A3g2PQAR",
      "createdByName": "Automated Process",
      "createdDate": "2020-08-20T22:27:35.000Z",
      "fileName": "reports/unfiled$public/flow_screen_prebuilt_report.report",
      "fullName": "unfiled$public/flow_screen_prebuilt_report",
      "id": "00O4W000003nxf8UAA",
      "lastModifiedById": "0054W00000A3g2PQAR",
      "lastModifiedByName": "Automated Process",
      "lastModifiedDate": "2020-08-20T22:27:35.000Z",
      "manageableState": "unmanaged",
      "type": "Report"
    },
    {
      "createdById": "0054W00000A3g2OQAR",
      "createdByName": "Admin User",
      "createdDate": "2020-08-20T22:27:35.000Z",
      "fileName": "reports/unfiled$public/SampleReportofOpenTasks.report",
      "fullName": "unfiled$public/SampleReportofOpenTasks",
      "id": "00O4W000002yTm0UAE",
      "lastModifiedById": "0054W00000A3g2OQAR",
      "lastModifiedByName": "Admin User",
      "lastModifiedDate": "2020-08-20T22:27:35.000Z",
      "manageableState": "unmanaged",
      "type": "Report"
    },
    {
      "createdById": "0054W00000A3g2OQAR",
      "createdByName": "Admin User",
      "createdDate": "2020-08-20T22:27:35.000Z",
      "fileName": "reports/unfiled$public/SampleReportofContacts.report",
      "fullName": "unfiled$public/SampleReportofContacts",
      "id": "00O4W000002yTlsUAE",
      "lastModifiedById": "0054W00000A3g2OQAR",
      "lastModifiedByName": "Admin User",
      "lastModifiedDate": "2020-08-20T22:27:35.000Z",
      "manageableState": "unmanaged",
      "type": "Report"
    },
    {
      "createdById": "0054W00000A3g2OQAR",
      "createdByName": "Admin User",
      "createdDate": "2020-08-20T22:27:35.000Z",
      "fileName": "reports/unfiled$public/SampleReportofTasksandActivities.report",
      "fullName": "unfiled$public/SampleReportofTasksandActivities",
      "id": "00O4W000002yTlwUAE",
      "lastModifiedById": "0054W00000A3g2OQAR",
      "lastModifiedByName": "Admin User",
      "lastModifiedDate": "2020-08-20T22:27:35.000Z",
      "manageableState": "unmanaged",
      "type": "Report"
    },
    {
      "createdById": "0054W00000A3g2OQAR",
      "createdByName": "Admin User",
      "createdDate": "2020-08-20T22:27:35.000Z",
      "fileName": "reports/unfiled$public/SampleReportofAccounts.report",
      "fullName": "unfiled$public/SampleReportofAccounts",
      "id": "00O4W000002yTm4UAE",
      "lastModifiedById": "0054W00000A3g2OQAR",
      "lastModifiedByName": "Admin User",
      "lastModifiedDate": "2020-08-20T22:27:35.000Z",
      "manageableState": "unmanaged",
      "type": "Report"
    },
    {
      "createdById": "0054W00000A3g2OQAR",
      "createdByName": "Admin User",
      "createdDate": "2020-08-20T22:27:35.000Z",
      "fileName": "reports/unfiled$public/SampleReportPipelineHistory.report",
      "fullName": "unfiled$public/SampleReportPipelineHistory",
      "id": "00O4W000003nxffUAA",
      "lastModifiedById": "0054W00000A3g2OQAR",
      "lastModifiedByName": "Admin User",
      "lastModifiedDate": "2020-08-20T22:27:35.000Z",
      "manageableState": "unmanaged",
      "type": "Report"
    },
    {
      "createdById": "0054W00000A3g2OQAR",
      "createdByName": "Admin User",
      "createdDate": "2020-08-20T22:27:35.000Z",
      "fileName": "reports/unfiled$public/SampleReportActiveUsers.report",
      "fullName": "unfiled$public/SampleReportActiveUsers",
      "id": "00O4W000002yTlvUAE",
      "lastModifiedById": "0054W00000A3g2OQAR",
      "lastModifiedByName": "Admin User",
      "lastModifiedDate": "2020-08-20T22:27:35.000Z",
      "manageableState": "unmanaged",
      "type": "Report"
    },
    {
      "createdById": "0054W00000A3g2OQAR",
      "createdByName": "Admin User",
      "createdDate": "2020-08-20T22:27:35.000Z",
      "fileName": "reports/unfiled$public/SampleReportLoginWallofShame.report",
      "fullName": "unfiled$public/SampleReportLoginWallofShame",
      "id": "00O4W000003nxfiUAA",
      "lastModifiedById": "0054W00000A3g2OQAR",
      "lastModifiedByName": "Admin User",
      "lastModifiedDate": "2020-08-20T22:27:35.000Z",
      "manageableState": "unmanaged",
      "type": "Report"
    },
    {
      "createdById": "0054W00000A3g2OQAR",
      "createdByName": "Admin User",
      "createdDate": "2020-08-20T22:27:35.000Z",
      "fileName": "reports/unfiled$public/SampleReportUsersLoggedIn.report",
      "fullName": "unfiled$public/SampleReportUsersLoggedIn",
      "id": "00O4W000002yTm2UAE",
      "lastModifiedById": "0054W00000A3g2OQAR",
      "lastModifiedByName": "Admin User",
      "lastModifiedDate": "2020-08-20T22:27:35.000Z",
      "manageableState": "unmanaged",
      "type": "Report"
    },
    {
      "createdById": "0054W00000A3g2OQAR",
      "createdByName": "Admin User",
      "createdDate": "2020-08-20T22:27:35.000Z",
      "fileName": "reports/unfiled$public/SampleReportLoginLeaderboard.report",
      "fullName": "unfiled$public/SampleReportLoginLeaderboard",
      "id": "00O4W000002yTm1UAE",
      "lastModifiedById": "0054W00000A3g2OQAR",
      "lastModifiedByName": "Admin User",
      "lastModifiedDate": "2020-08-20T22:27:35.000Z",
      "manageableState": "unmanaged",
      "type": "Report"
    },
    {
      "createdById": "0054W00000A3g2OQAR",
      "createdByName": "Admin User",
      "createdDate": "2020-08-20T22:27:35.000Z",
      "fileName": "reports/unfiled$public/SampleReportofReports.report",
      "fullName": "unfiled$public/SampleReportofReports",
      "id": "00O4W000003nxfhUAA",
      "lastModifiedById": "0054W00000A3g2OQAR",
      "lastModifiedByName": "Admin User",
      "lastModifiedDate": "2020-08-20T22:27:35.000Z",
      "manageableState": "unmanaged",
      "type": "Report"
    },
    {
      "createdById": "0054W00000A3g2OQAR",
      "createdByName": "Admin User",
      "createdDate": "2020-08-20T22:27:35.000Z",
      "fileName": "reports/unfiled$public/SampleReportMonthtoDateTrending.report",
      "fullName": "unfiled$public/SampleReportMonthtoDateTrending",
      "id": "00O4W000003nxfeUAA",
      "lastModifiedById": "0054W00000A3g2OQAR",
      "lastModifiedByName": "Admin User",
      "lastModifiedDate": "2020-08-20T22:27:35.000Z",
      "manageableState": "unmanaged",
      "type": "Report"
    },
    {
      "createdById": "0054W00000A3g2OQAR",
      "createdByName": "Admin User",
      "createdDate": "2020-08-20T22:27:35.000Z",
      "fileName": "reports/unfiled$public/SampleReportCompletedActivities.report",
      "fullName": "unfiled$public/SampleReportCompletedActivities",
      "id": "00O4W000002yTm3UAE",
      "lastModifiedById": "0054W00000A3g2OQAR",
      "lastModifiedByName": "Admin User",
      "lastModifiedDate": "2020-08-20T22:27:35.000Z",
      "manageableState": "unmanaged",
      "type": "Report"
    },
    {
      "createdById": "0054W00000A3g2OQAR",
      "createdByName": "Admin User",
      "createdDate": "2020-08-20T22:27:35.000Z",
      "fileName": "reports/unfiled$public/SampleReportOpenCasesByPriority.report",
      "fullName": "unfiled$public/SampleReportOpenCasesByPriority",
      "id": "00O4W000003nxfVUAQ",
      "lastModifiedById": "0054W00000A3g2OQAR",
      "lastModifiedByName": "Admin User",
      "lastModifiedDate": "2020-08-20T22:27:35.000Z",
      "manageableState": "unmanaged",
      "type": "Report"
    },
    {
      "createdById": "0054W00000A3g2OQAR",
      "createdByName": "Admin User",
      "createdDate": "2020-08-20T22:27:35.000Z",
      "fileName": "reports/unfiled$public/SampleReportCustomReportsbyUser.report",
      "fullName": "unfiled$public/SampleReportCustomReportsbyUser",
      "id": "00O4W000002yTlzUAE",
      "lastModifiedById": "0054W00000A3g2OQAR",
      "lastModifiedByName": "Admin User",
      "lastModifiedDate": "2020-08-20T22:27:35.000Z",
      "manageableState": "unmanaged",
      "type": "Report"
    },
    {
      "createdById": "0054W00000A3g2OQAR",
      "createdByName": "Admin User",
      "createdDate": "2020-08-20T22:27:35.000Z",
      "fileName": "reports/unfiled$public/SampleReportsLeadsbyStatus.report",
      "fullName": "unfiled$public/SampleReportsLeadsbyStatus",
      "id": "00O4W000003nxfdUAA",
      "lastModifiedById": "0054W00000A3g2OQAR",
      "lastModifiedByName": "Admin User",
      "lastModifiedDate": "2020-08-20T22:27:35.000Z",
      "manageableState": "unmanaged",
      "type": "Report"
    },
    {
      "createdById": "0054W00000A3g2OQAR",
      "createdByName": "Admin User",
      "createdDate": "2020-08-20T22:27:35.000Z",
      "fileName": "reports/unfiled$public/SampleReportTopAccounts.report",
      "fullName": "unfiled$public/SampleReportTopAccounts",
      "id": "00O4W000003nxfZUAQ",
      "lastModifiedById": "0054W00000A3g2OQAR",
      "lastModifiedByName": "Admin User",
      "lastModifiedDate": "2020-08-20T22:27:35.000Z",
      "manageableState": "unmanaged",
      "type": "Report"
    },
    {
      "createdById": "0054W00000A3g2OQAR",
      "createdByName": "Admin User",
      "createdDate": "2020-08-20T22:27:35.000Z",
      "fileName": "reports/unfiled$public/SampleReportSolutionsAdded.report",
      "fullName": "unfiled$public/SampleReportSolutionsAdded",
      "id": "00O4W000003nxfaUAA",
      "lastModifiedById": "0054W00000A3g2OQAR",
      "lastModifiedByName": "Admin User",
      "lastModifiedDate": "2020-08-20T22:27:35.000Z",
      "manageableState": "unmanaged",
      "type": "Report"
    },
    {
      "createdById": "0054W00000A3g2OQAR",
      "createdByName": "Admin User",
      "createdDate": "2020-08-20T22:27:35.000Z",
      "fileName": "reports/unfiled$public/SampleReportofCases.report",
      "fullName": "unfiled$public/SampleReportofCases",
      "id": "00O4W000002yTlrUAE",
      "lastModifiedById": "0054W00000A3g2OQAR",
      "lastModifiedByName": "Admin User",
      "lastModifiedDate": "2020-08-20T22:27:35.000Z",
      "manageableState": "unmanaged",
      "type": "Report"
    }
  ]
}